[
  {
    "id": 1,
    "chapter": "运营风险与内控",
    "text": "银企对账形成的档案资料，应按会计档案管理的相关规定妥善保管。包括但不限于以下内容( )",
    "options": [
      "对账电子数据",
      "银企对账回执(含余额调节表)",
      "对账单交接登记簿",
      "其他需要保管的对账资料"
    ],
    "answer": [
      0,
      1,
      2,
      3
    ],
    "type": "multi",
    "note": ""
  },
  {
    "id": 2,
    "chapter": "存款与储蓄业务",
    "text": "有权查询、冻结、扣划单位、个人储蓄存款的单位包括( )。",
    "options": [
      "人民法院",
      "税务机关",
      "海关",
      "监察机关"
    ],
    "answer": [
      0,
      1,
      2
    ],
    "type": "multi",
    "note": ""
  },
  {
    "id": 3,
    "chapter": "其他",
    "text": "客服经理考核主要包括( ) 等内容，并根据实际业务权限、工作负荷，工作难度等因素科学选取考核指标及权重，完整反映客服经理工作负荷和实际业绩。",
    "options": [
      "厅堂服务",
      "客户维护和营销推介",
      "柜面业务工作量",
      "智能核验",
      "核算质效"
    ],
    "answer": [
      0,
      1,
      2,
      3,
      4
    ],
    "type": "multi",
    "note": ""
  },
  {
    "id": 4,
    "chapter": "现金业务与自助机具",
    "text": "营业网点钱箱管理必须严格执行现金业务操作规程，坚持( )。",
    "options": [
      "“9999钱箱”实物双人管理",
      "共同负责",
      "日终双人结账",
      "现金实物、钱箱查询余额、网点现金日结单相核对"
    ],
    "answer": [
      0,
      1,
      2,
      3
    ],
    "type": "multi",
    "note": ""
  },
  {
    "id": 5,
    "chapter": "个人外汇业务",
    "text": "我行跨境电汇收费标准为:按汇出金额的( )收取，最低50元/笔，最高( )元/笔;电讯费: 150元/笔。",
    "options": [
      "1.5%o",
      "1%o",
      "200",
      "260"
    ],
    "answer": [
      1,
      3
    ],
    "type": "multi",
    "note": ""
  },
  {
    "id": 6,
    "chapter": "存款与储蓄业务",
    "text": "联名账户种类为开立在借记卡下的人民币活期存款结算账户或人民币整存整取定期储蓄存款账户( )。",
    "options": [
      "人民币活期存款结算账户",
      "人民币整存整取定期储蓄存款账户",
      "多币种活期存款结算账户",
      "多币种整存整取定期储蓄存款账户"
    ],
    "answer": [
      0,
      1
    ],
    "type": "multi",
    "note": ""
  },
  {
    "id": 7,
    "chapter": "厅堂与客户服务",
    "text": "智能PAD“工银E服务”APP的主要功能包括( )。",
    "options": [
      "现场业务审核",
      "优质客户识别",
      "厅堂服务管理",
      "业务知识查询学习"
    ],
    "answer": [
      0,
      1,
      2,
      3
    ],
    "type": "multi",
    "note": ""
  },
  {
    "id": 8,
    "chapter": "基金业务",
    "text": "以下关于基金专户的说法，正确的是( )",
    "options": [
      "基金专户认购起点不低于100 万元，单只基金专户的投资者人数不超过200人",
      "不得通过报刊、电台、电视台、互联网等公众传播媒体或者讲座、报告会、分析会等方式向不特定对象宣传推介资产管理计划",
      "基金专户的业绩基准是指管理人承诺的一定能实现的产品收益",
      "不得向投资人承诺资产管理计划的本金不受损失或承诺最低收益"
    ],
    "answer": [
      0,
      1,
      3
    ],
    "type": "multi",
    "note": ""
  },
  {
    "id": 9,
    "chapter": "运营风险与内控",
    "text": "凭证预售处理包括( )模式。",
    "options": [
      "网上预约处理",
      "集中预售处理",
      "跨网点预售处理",
      "分散预售处理"
    ],
    "answer": [
      0,
      3
    ],
    "type": "multi",
    "note": ""
  },
  {
    "id": 10,
    "chapter": "电子银行业务",
    "text": "为了确保网络安全，我行除了为个人网上银行客户提供U盾、电子银行口令卡、工银电子密码器等安全手段外，还提供了( ) 等网上银行安全保护手段。",
    "options": [
      "余额变动提醒",
      "预留验证信息",
      "防钓鱼安全控件",
      "账户安全锁"
    ],
    "answer": [
      0,
      1,
      2,
      3
    ],
    "type": "multi",
    "note": ""
  },
  {
    "id": 11,
    "chapter": "其他",
    "text": "对禁止类客户应采取严格的风险控制措施，包括( )。",
    "options": [
      "停止金融账户的开立、变更、撤销和使用",
      "停止金融交易，拒绝转移、转换金融资产",
      "依法冻结在本行的金融资产",
      "及时将有关情况报告总行"
    ],
    "answer": [
      0,
      1,
      2,
      3
    ],
    "type": "multi",
    "note": ""
  },
  {
    "id": 12,
    "chapter": "个人外汇业务",
    "text": "境内机构对一家境外投资企业的投资款，可选择在( ) 办理资金汇出。",
    "options": [
      "同一家银行的不同网点",
      "同一-家银行的同一网点",
      "不同银行",
      "投资性公司"
    ],
    "answer": [
      0,
      1,
      2
    ],
    "type": "multi",
    "note": ""
  },
  {
    "id": 13,
    "chapter": "电子银行业务",
    "text": "我行的通用U盾可以在以下哪些电子银行产品中应用? ( )",
    "options": [
      "个人网上银行",
      "短信银行",
      "手机银行",
      "个人电话银行"
    ],
    "answer": [
      0,
      1,
      2,
      3
    ],
    "type": "multi",
    "note": ""
  },
  {
    "id": 14,
    "chapter": "其他",
    "text": "集中处理成功的业务回单，可由客户通过( ) 打印，或客服经理通过( ) 等方式打印。A.前台报表系统",
    "options": [
      "自助设备",
      "相关交易",
      "集中打印"
    ],
    "answer": [
      0,
      1,
      2
    ],
    "type": "multi",
    "note": ""
  },
  {
    "id": 15,
    "chapter": "票据结算",
    "text": "以下对支票的使用说法正确的选项是( )",
    "options": [
      "提示付款期限自出票日起10天，超过提示付款期的银行不予受理",
      "出票人预留银行签章是银行审核支票付款的依据，也可以使用支付密码，作为银行审核支付支票金额的条件之一",
      "出票人预留银行签章是银行审核支票付款的依据，也可以使用支付密码，作为银行审核支付支票金额的必要条件之一",
      "持票人将支票交开户银行收款时，应做转让背书",
      "持票人将支票交开户银行收款时，应使用炭素墨水或墨汁填写"
    ],
    "answer": [
      0,
      1,
      4
    ],
    "type": "multi",
    "note": ""
  },
  {
    "id": 16,
    "chapter": "电子银行业务",
    "text": "个人客户注册电子银行，向客户发放U盾时，现场授权人员或现场管理人员应( )。",
    "options": [
      "应审核《通用机打凭证》(处理结果)上打印的U盾序列号与发放给客户的序号-一致，",
      "监督业务经办人员将U盾发放给客户本人",
      "监督U盾发放给客户本人且客户本人签收后，在《通用机打凭证》(处理结果)上签章。D.向客户发放安全宣传折页(手册)"
    ],
    "answer": [
      0,
      1
    ],
    "type": "multi",
    "note": ""
  },
  {
    "id": 17,
    "chapter": "其他",
    "text": "处理客户意见工单需遵循以下原则( )",
    "options": [
      "快速响应处理",
      "客观全面核实",
      "公平公正归责",
      "有效妥善处置"
    ],
    "answer": [
      0,
      1,
      2,
      3
    ],
    "type": "multi",
    "note": ""
  },
  {
    "id": 18,
    "chapter": "存款与储蓄业务",
    "text": "关于通知存款存期计算的规则说法正确的有( )。",
    "options": [
      "对已办理通知手续而未支取或在通知期限内取消通知的，通知期限内按照活期利率计息B.通知存款存期按起息日算起至支取日前一-天为止",
      "通知存款按照实际天数和通知存款日利率计算利息",
      "个人通知存款应约定提前通知取款时间，不约定存期"
    ],
    "answer": [
      1,
      2,
      3
    ],
    "type": "multi",
    "note": ""
  },
  {
    "id": 19,
    "chapter": "账户管理",
    "text": "借记卡换卡后，需进行账户调整或到相关单位进行变更的有( )",
    "options": [
      "第三方存管",
      "信用卡自动还款协议",
      "理财协议",
      "代发工资协议"
    ],
    "answer": [
      0,
      1,
      3
    ],
    "type": "multi",
    "note": ""
  },
  {
    "id": 20,
    "chapter": "其他",
    "text": "智能管户方案在PBMS系统有哪几个( ) 功能板块",
    "options": [
      "专属管户方案",
      "客户维护任务",
      "智能零售"
    ],
    "answer": [
      0,
      1,
      2
    ],
    "type": "multi",
    "note": ""
  },
  {
    "id": 21,
    "chapter": "其他",
    "text": "按照登记簿使用规定，下列对登记簿的记载内容不允许的行为是( )。",
    "options": [
      "涂改",
      "皮擦",
      "使用涂改液销蚀",
      "挖补、刀刮"
    ],
    "answer": [
      0,
      1,
      2,
      3
    ],
    "type": "multi",
    "note": ""
  },
  {
    "id": 22,
    "chapter": "运营风险与内控",
    "text": "会计凭证档案影像管理系统是集会计凭证档案( )等功能于一一体。",
    "options": [
      "影像采集",
      "索引建立",
      "数据储存",
      "档案应用"
    ],
    "answer": [
      0,
      1,
      2,
      3
    ],
    "type": "multi",
    "note": ""
  },
  {
    "id": 23,
    "chapter": "其他",
    "text": "客户更改开户证件，造成其身份证件类型或号码变更，申请变更调整，( ),营业网点能够确定为同一人时不需要出具证明，仅须携带本人有效身份证件即可。",
    "options": [
      "当基层网点无法确认军官证真实性，或者凭军官证及身份证无法认定为同一人时",
      "客户持有居民身份证、户口簿、临时身份证之一并且后续变更为另一种证件时",
      "客户曾经使用15 位居民身份证至我行办理业务，现更换为18位(仅升位)居民身份证时",
      "港澳居民往来内地通行证、台湾居民来往大陆通行证持有人姓名不变，证件号码中仅标志换证次数的两位变化时"
    ],
    "answer": [
      1,
      2,
      3
    ],
    "type": "multi",
    "note": ""
  },
  {
    "id": 24,
    "chapter": "运营风险与内控",
    "text": "当客户办理预售凭证领取时，客服经理应审核《预约订单》上是否加盖( )的身份证件。A.预留印鉴",
    "options": [
      "公章",
      "法人"
    ],
    "answer": [
      0,
      3
    ],
    "type": "multi",
    "note": ""
  },
  {
    "id": 25,
    "chapter": "其他",
    "text": "签批是指业务主管部门有权人对需要审批的重要业务事项进行( )的管理方式。",
    "options": [
      "签字批准",
      "系统处理",
      "电子审批",
      "现场处理"
    ],
    "answer": [
      0,
      2
    ],
    "type": "multi",
    "note": ""
  },
  {
    "id": 26,
    "chapter": "厅堂与客户服务",
    "text": "“工银薪管家”综合服务是面向代发工资客户搭建的统一营销服务平台，主要包括“薪金卡”、“薪金溢”、“薪金贷”、( ) 等特色服务。",
    "options": [
      "薪金享",
      "薪金惠",
      "薪金通",
      "薪金富"
    ],
    "answer": [
      0,
      1,
      2
    ],
    "type": "multi",
    "note": ""
  },
  {
    "id": 27,
    "chapter": "其他",
    "text": "客服经理对目标客户日常维护工作内容包括",
    "options": [
      "节日、生日、特别纪念日慰问",
      "关联销售",
      "不定期开展小型客户调查活动",
      "提醒服务"
    ],
    "answer": [
      0,
      1,
      2,
      3
    ],
    "type": "multi",
    "note": ""
  },
  {
    "id": 28,
    "chapter": "现金业务与自助机具",
    "text": "以下关于24小时自助银行管理的表述正确的是( )",
    "options": [
      "管理网点应定期对自助银行内外部环境进行清洁，确保自助银行服务环境优美，无违规张贴物，方便运营维护和客户办理业务",
      "有条件的离行式自助银行应设置无障碍通道，方便特殊客户进出",
      "各类设备线路铺设应有护线保护措施，防止线缆外露，接插件应置于封闭的刚性防护体内答案: ABCD"
    ],
    "answer": [
      0,
      1,
      2,
      3
    ],
    "type": "multi",
    "note": ""
  },
  {
    "id": 29,
    "chapter": "其他",
    "text": "单位申办商务卡应提供的基本资料包括(",
    "options": [
      "完整填写并加盖单位公章的申请表",
      "银行《开户许可证》复印件",
      "单位卡指定持卡人身份证件复印件",
      "单位卡申请单位法定代表人(负责人)身份证件复印件"
    ],
    "answer": [
      0,
      1,
      2,
      3
    ],
    "type": "multi",
    "note": ""
  },
  {
    "id": 30,
    "chapter": "运营风险与内控",
    "text": "按照人民银行要求统-设计的会计核算专用印章包括( )等。",
    "options": [
      "代理财税专用章",
      "汇票专用章",
      "华东三省-市汇票专用章",
      "本票专用章",
      "假币鉴定专用章"
    ],
    "answer": [
      1,
      2,
      3,
      4
    ],
    "type": "multi",
    "note": ""
  },
  {
    "id": 31,
    "chapter": "其他",
    "text": "专属管户方案提供该产品的交易推送方式有哪几种( )",
    "options": [
      "生成二维码",
      "融E联",
      "微信推送",
      "电话外拨"
    ],
    "answer": [
      0,
      1,
      2,
      3
    ],
    "type": "multi",
    "note": ""
  },
  {
    "id": 32,
    "chapter": "账户管理",
    "text": "某单位客户法定代表人变动，向银行申请进行相应的变更手续。客服经理得知该客户在本网点开立账户属性为一般户。客服经理所进行的业务处理应包含( )。",
    "options": [
      "登录人民银行账户管理系统查询客户是否已进行基本账户信息的变更",
      "和现场管理人员审查客户所提交变更申请资料的真实性、完整性和合规性",
      "在复印件上注明“与原件核对一致”字样，并由客服经理和现场管理人员在变更申请书和变更资料上双人签章",
      "及时将《变更申请书》、开户许可证及相关证明文件报送人民银行当地分支行"
    ],
    "answer": [
      0,
      1,
      2
    ],
    "type": "multi",
    "note": ""
  },
  {
    "id": 33,
    "chapter": "运营风险与内控",
    "text": "在办理集中处理业务时，对于经审查后符合制度规定的业务，应使用相关交易录入业务信息，正确选择凭证版式，将与业务相关的( ) 等资料扫描上传至集中平台。",
    "options": [
      "记账凭证",
      "会计报表",
      "原始依据",
      "影像资料"
    ],
    "answer": [
      0,
      2
    ],
    "type": "multi",
    "note": ""
  },
  {
    "id": 34,
    "chapter": "运营风险与内控",
    "text": "可采用系统驱动电子印章方式的会计核算专用印章包括( )。",
    "options": [
      "汇票专用章",
      "业务专用章",
      "代理财税专用章",
      "结算专用章"
    ],
    "answer": [
      1,
      2
    ],
    "type": "multi",
    "note": ""
  },
  {
    "id": 35,
    "chapter": "现金业务与自助机具",
    "text": "我行电子现金圈存的渠道有: ( )。",
    "options": [
      "网点柜面",
      "POS机具",
      "网上银行",
      "电话银行"
    ],
    "answer": [
      0,
      1,
      2
    ],
    "type": "multi",
    "note": ""
  },
  {
    "id": 36,
    "chapter": "现金业务与自助机具",
    "text": "系统内现金调拨方式主要包括( )。",
    "options": [
      "营业网点从中心库或支行业务库调入现金",
      "营业网点向中心库或支行业务库调出现金",
      "支行业务库从中心库调入现金",
      "支行业务库向中心库调出现金",
      "营业网点之间的现金调拨"
    ],
    "answer": [
      0,
      1,
      2,
      3,
      4
    ],
    "type": "multi",
    "note": ""
  },
  {
    "id": 37,
    "chapter": "反洗钱与大额交易",
    "text": "反洗钱秘密信息管理包括( )、涉密岗位交换、涉密事件报告等。",
    "options": [
      "保密工作设施配备",
      "涉密信息文件的处理",
      "涉密信息传输",
      "涉密废件销毁"
    ],
    "answer": [
      0,
      1,
      2,
      3
    ],
    "type": "multi",
    "note": ""
  },
  {
    "id": 38,
    "chapter": "厅堂与客户服务",
    "text": "以下关于网点客户服务“客户为尊”原则的表述正确的是( )",
    "options": [
      "在整个服务旅程中始终让客户感受到尊重。尊重客户意愿和知情权",
      "尊重客户意愿和知情权，不误导、欺骗客户，不生硬拒绝客户",
      "遵循先外后内的操作原则",
      "善于从客户角度换位思考,站在客户的立场采取客户欣于接受的服务方式"
    ],
    "answer": [
      0,
      1,
      2,
      3
    ],
    "type": "multi",
    "note": ""
  },
  {
    "id": 39,
    "chapter": "其他",
    "text": "以下哪些岗位人员可以具有主机业务审核权限?",
    "options": [
      "网点负责人",
      "客户经理",
      "运营主管",
      "客服经理"
    ],
    "answer": [
      0,
      2
    ],
    "type": "multi",
    "note": ""
  },
  {
    "id": 40,
    "chapter": "其他",
    "text": "金额在( ) (含)元以上的表内业务，金额在( ) (含)元以上的表外业务，应由业务授权人员进行审核签批的业务。",
    "options": [
      "5万元",
      "10万元",
      "1万元",
      "50万元"
    ],
    "answer": [
      1,
      2
    ],
    "type": "multi",
    "note": ""
  },
  {
    "id": 41,
    "chapter": "其他",
    "text": "以下哪些是长城系列“随心E”产品的特点?",
    "options": [
      "收益好较同类产品高",
      "购买起点5万，起点低",
      "支持当日赎回，资金实时入账",
      "每个工作日可购买"
    ],
    "answer": [
      0,
      1,
      3
    ],
    "type": "multi",
    "note": ""
  },
  {
    "id": 42,
    "chapter": "厅堂与客户服务",
    "text": "“商旅金融”服务方案的目标客户主要是个人旅游类客户及公派出国等集群类客户。出国旅游商务活动可分为行前、出行、归国三个阶段，具体产品包括( )",
    "options": [
      "个人资信证明",
      "代发工资业务",
      "工银环球旅行卡",
      "出国金融卡"
    ],
    "answer": [
      0,
      2,
      3
    ],
    "type": "multi",
    "note": ""
  },
  {
    "id": 43,
    "chapter": "其他",
    "text": "轧账是指通过在系统中录入相关业务数据，完成系统账务处理正确性、完整性核对的过程。客服经理在营业中离开网点或营业终了离开网点前，均应进行轧账。日终轧账包括( )。",
    "options": [
      "客服经理轧账",
      "现金轧账",
      "转账轧账",
      "网点轧账"
    ],
    "answer": [
      0,
      3
    ],
    "type": "multi",
    "note": ""
  },
  {
    "id": 44,
    "chapter": "其他",
    "text": "业务集中受理扫描人员应按照有关制度规定对( )和相关资料进行严格审查，认真做好防伪鉴别。",
    "options": [
      "客户身份",
      "银行介质",
      "客户密码",
      "业务凭证"
    ],
    "answer": [
      0,
      1,
      3
    ],
    "type": "multi",
    "note": ""
  },
  {
    "id": 45,
    "chapter": "其他",
    "text": "在智能PAD保管方面，如下哪些行为应被禁止?",
    "options": [
      "将本人统一一认证号及密码交他人登陆使用",
      "将未签退的智能PAD交他人保管和审核业务",
      "使用他人统一一认证号及密码登陆并审核业务等",
      "安装非我行授权应用软件和使用非我行授权存储设备",
      "营业终了未签退统--认证系统"
    ],
    "answer": [
      0,
      1,
      2,
      3,
      4
    ],
    "type": "multi",
    "note": ""
  },
  {
    "id": 46,
    "chapter": "账户管理",
    "text": "住房公积金专户是指住房公积金管理中心在我行设立的记载和反映住房公积金( )等资金情况的专门账户。",
    "options": [
      "缴存",
      "提取",
      "使用",
      "结算"
    ],
    "answer": [
      0,
      1,
      2,
      3
    ],
    "type": "multi",
    "note": ""
  },
  {
    "id": 47,
    "chapter": "运营风险与内控",
    "text": "凭证预售线上渠道包含( )。",
    "options": [
      "企业网上银行",
      "企业电话银行",
      "自助设备",
      "网点柜面"
    ],
    "answer": [
      0,
      1,
      2
    ],
    "type": "multi",
    "note": ""
  },
  {
    "id": 48,
    "chapter": "票据结算",
    "text": "以下对于银行本票的说法正确的是( )",
    "options": [
      "银行本票可以用于转账，注明“现金”字样的银行本票可以用于支取现金。",
      "现金银行本票仅限系统内银行兑付，可以转让。",
      "本票上未划去“现金”和“转账”字样的，- -律按照转账银行本票办理。",
      "申请人或收款人为单位的，不得申请签发现金银行本票。"
    ],
    "answer": [
      0,
      2,
      3
    ],
    "type": "multi",
    "note": ""
  },
  {
    "id": 49,
    "chapter": "票据结算",
    "text": "企业电话银行为客户提供验证支票支付密码功能，可验证( )等票据的支付密码。A.现金支票",
    "options": [
      "转账支票",
      "汇票委托书",
      "电汇凭证"
    ],
    "answer": [
      0,
      1,
      2,
      3
    ],
    "type": "multi",
    "note": ""
  },
  {
    "id": 50,
    "chapter": "其他",
    "text": "工行手机银行采取( )等手段确保客户资金与信息的安全。",
    "options": [
      "工银电子密码器",
      "一代U盾",
      "通用U盾",
      "IC卡证书"
    ],
    "answer": [
      0,
      1,
      2
    ],
    "type": "multi",
    "note": ""
  },
  {
    "id": 51,
    "chapter": "账户管理",
    "text": "以下业务，均使用卡下基本账户的有( ).",
    "options": [
      "持卡消费",
      "自动柜员机办理现金存取款",
      "年费扣收",
      "小额账，户管理费扣收"
    ],
    "answer": [
      0,
      1,
      2,
      3
    ],
    "type": "multi",
    "note": ""
  },
  {
    "id": 52,
    "chapter": "厅堂与客户服务",
    "text": "关于柜面服务规范的描述正确的是( )",
    "options": [
      "在办理收费业务时，提前告知客户服务项目和收费标准",
      "主动告知客户费用减免渠道或方式，充分尊重客户知情权，且实际收取的服务价格与公告相符C.需要客户签字时，主动提示客户核对业务凭证或双屏上的交易信息，并指导签字",
      "办理现金业务时，及时提醒客户清点核对"
    ],
    "answer": [
      0,
      1,
      2,
      3
    ],
    "type": "multi",
    "note": ""
  },
  {
    "id": 53,
    "chapter": "账户管理",
    "text": "同业客户购买理财产品须开立( )账户",
    "options": [
      "同业投融资账户",
      "理财交易账户",
      "同业存款专户",
      "托管账户"
    ],
    "answer": [
      0,
      1
    ],
    "type": "multi",
    "note": ""
  },
  {
    "id": 54,
    "chapter": "运营风险与内控",
    "text": "对已纳入柜面用印机保管的会计核算专用印章，仅在遇到( )等情况时方可取出。",
    "options": [
      "系统或设备故障导致无法正常用印",
      "印章清洁",
      "印章停用",
      "用印次数较多"
    ],
    "answer": [
      0,
      1,
      2
    ],
    "type": "multi",
    "note": ""
  },
  {
    "id": 55,
    "chapter": "其他",
    "text": "专属管户方案包括哪几类产品( )",
    "options": [
      "基础类",
      "投资类",
      "融资类",
      "增值类"
    ],
    "answer": [
      0,
      1,
      2,
      3
    ],
    "type": "multi",
    "note": ""
  },
  {
    "id": 56,
    "chapter": "运营风险与内控",
    "text": "会计核算专用印章的用印方式包括( )。",
    "options": [
      "签批用印",
      "自主用印",
      "系统驱动电子印章",
      "系统驱动自动化用印"
    ],
    "answer": [
      0,
      2,
      3
    ],
    "type": "multi",
    "note": ""
  },
  {
    "id": 57,
    "chapter": "其他",
    "text": "电子对账单按约定周期发送至客户( )。",
    "options": [
      "网上银行",
      "电话银行",
      "银企互联系统",
      "自助回单设备"
    ],
    "answer": [
      0,
      2,
      3
    ],
    "type": "multi",
    "note": ""
  },
  {
    "id": 58,
    "chapter": "电子银行业务",
    "text": "二代U盾客户可以使用的安全辅助工具包括( )",
    "options": [
      "口令卡和计算机绑定",
      "余额变动提醒",
      "手机短信认证",
      "预留信息验证"
    ],
    "answer": [
      1,
      3
    ],
    "type": "multi",
    "note": ""
  },
  {
    "id": 59,
    "chapter": "其他",
    "text": "以下关于客户意见簿管理的描述正确的是( )",
    "options": [
      "网点应在显著位置摆放客户意见簿，页码连续、内容完整、格式规范，方便客户反映意见B.有条件和有需要的网点可配置中英文双语或少数民族语言客户意见簿",
      "网点负责人应于每日营业终了时查阅一次客户意见簿，并在客户意见簿中记录查阅情况，对当日客户所留意见及时予以回复",
      "对留有电话的客户应回拨答复，回复不得随意，不得敷衍搪塞客户，重在针对客户的关切提出措施，解决问题"
    ],
    "answer": [
      0,
      1,
      2,
      3
    ],
    "type": "multi",
    "note": ""
  },
  {
    "id": 60,
    "chapter": "反洗钱与大额交易",
    "text": "发送和接收纸质反洗钱秘密信息应当做好( ), 并妥善保存。",
    "options": [
      "记录",
      "签收",
      "复印",
      "转发"
    ],
    "answer": [
      0,
      1
    ],
    "type": "multi",
    "note": ""
  },
  {
    "id": 61,
    "chapter": "厅堂与客户服务",
    "text": "以下属于服务行为“十严禁”内容的是( )",
    "options": [
      "在基金、理财、保险、贵金属等投资性金融产品销售过程中误导、欺诈客户或违反规定程序销售B.故意不按照客户的业务办理意愿，擅自为客户开通服务项目或购买金融产品等",
      "擅自代替客户对服务进行评价，无人管理值守网点厅堂，对到店客户不管不问",
      "处理投诉推诿敷衍，层层推脱，不切实有效解决客户合理诉求"
    ],
    "answer": [
      0,
      1,
      2,
      3
    ],
    "type": "multi",
    "note": ""
  },
  {
    "id": 62,
    "chapter": "运营风险与内控",
    "text": "会计凭证应具备下列基本要素: ( )、收付款人的开户行名称、款项用途、摘要及附件张数、客户签章、银行及有关人员签章等。",
    "options": [
      "凭证日期",
      "凭证印刷日期",
      "货币符号和大小写金额",
      "户名和账号"
    ],
    "answer": [
      0,
      2,
      3
    ],
    "type": "multi",
    "note": ""
  },
  {
    "id": 63,
    "chapter": "其他",
    "text": "办理汇兑业务可以通过( )的方式实现。",
    "options": [
      "系统内本外币回话",
      "跨行支付系统",
      "同城票据交换",
      "支票影像交换系统"
    ],
    "answer": [
      0,
      1,
      2
    ],
    "type": "multi",
    "note": ""
  },
  {
    "id": 64,
    "chapter": "其他",
    "text": "按贷款风险状况分类，我行贷款可分为( )。",
    "options": [
      "正常贷款",
      "关注贷款",
      "次级贷款",
      "可疑贷款",
      "损失贷款"
    ],
    "answer": [
      0,
      1,
      2,
      3,
      4
    ],
    "type": "multi",
    "note": ""
  },
  {
    "id": 65,
    "chapter": "其他",
    "text": "开户行受理单位客户变更预留印鉴申请的，应审核( )和( ),方可发放新预留印鉴卡。A.单位客户有权人身份证件",
    "options": [
      "单位法人身份证件",
      "领取新预留印鉴卡的公函",
      "印鉴领取单"
    ],
    "answer": [
      0,
      2
    ],
    "type": "multi",
    "note": ""
  },
  {
    "id": 66,
    "chapter": "其他",
    "text": "客服经理使用“密码重置”交易，摘要选择“延时重置”，按照系统提示输入账号( )等相关要素，经有权人审核授权后会同客服经理办理。",
    "options": [
      "储户姓名",
      "储蓄金额",
      "储户证件类型",
      "储户证件号码"
    ],
    "answer": [
      0,
      2,
      3
    ],
    "type": "multi",
    "note": ""
  },
  {
    "id": 67,
    "chapter": "运营风险与内控",
    "text": "网点分散采集模式是通过新终端交易进行凭证影像的扫描(或拍照)，分为( )和( )两种情况。",
    "options": [
      "有流水号",
      "索引建立",
      "无流水号",
      "档案应用"
    ],
    "answer": [
      0,
      2
    ],
    "type": "multi",
    "note": ""
  },
  {
    "id": 68,
    "chapter": "其他",
    "text": "金融机构不得出具与事实不符的( )等金融票证。",
    "options": [
      "信用证",
      "TT",
      "保函",
      "存单"
    ],
    "answer": [
      0,
      2,
      3
    ],
    "type": "multi",
    "note": ""
  },
  {
    "id": 69,
    "chapter": "厅堂与客户服务",
    "text": "营业网点服务客户遵循以下哪些原则( )",
    "options": [
      "客户为尊",
      "效率优先",
      "专业周到",
      "臻于细节"
    ],
    "answer": [
      0,
      1,
      2,
      3
    ],
    "type": "multi",
    "note": ""
  },
  {
    "id": 70,
    "chapter": "厅堂与客户服务",
    "text": "智能PAD“工银E服务”APP的厅堂服务功能包括( )。",
    "options": [
      "柜面排号销号",
      "现场监控",
      "客户安全介质信息查询",
      "功能设置"
    ],
    "answer": [
      0,
      1,
      2,
      3
    ],
    "type": "multi",
    "note": ""
  },
  {
    "id": 71,
    "chapter": "其他",
    "text": "注重客户第一满意度，包括",
    "options": [
      "注重客户的试探性满意度",
      "注重每一笔业务的首次满意度",
      "注重客户在第--时间的满意度",
      "注重客户业务范围之外需求的满意度"
    ],
    "answer": [
      0,
      1,
      2,
      3
    ],
    "type": "multi",
    "note": ""
  },
  {
    "id": 72,
    "chapter": "票据结算",
    "text": "票据贴现业务，包括( )的贴现。",
    "options": [
      "银行承兑汇票的贴现",
      "商业承兑汇票的贴现",
      "银行本票的贴现",
      "银行汇票的贴现"
    ],
    "answer": [
      0,
      4
    ],
    "type": "multi",
    "note": ""
  },
  {
    "id": 73,
    "chapter": "其他",
    "text": "对于业务处理中心处理成功的集中处理业务，网点客服经理后续处理包含( )。",
    "options": [
      "凭证、票据打印",
      "现金配款",
      "报表核对",
      "回单打印"
    ],
    "answer": [
      0,
      1,
      3
    ],
    "type": "multi",
    "note": ""
  },
  {
    "id": 74,
    "chapter": "其他",
    "text": "会计影像档案管理系统是具有( ) 特征的电子影像管理平台",
    "options": [
      "逻辑统一",
      "精确索引",
      "综合利用",
      "管理高效"
    ],
    "answer": [
      0,
      1,
      2,
      3
    ],
    "type": "multi",
    "note": ""
  },
  {
    "id": 75,
    "chapter": "存款与储蓄业务",
    "text": "个人存款创新产品“薪金溢3号”产品的期限包括( )",
    "options": [
      "1年",
      "2年",
      "3年",
      "5年"
    ],
    "answer": [
      0,
      2,
      3
    ],
    "type": "multi",
    "note": ""
  },
  {
    "id": 76,
    "chapter": "账户管理",
    "text": "活期账户的联名账户所有人可对联名账户开户时约定的部分内容办理变更业务。可变更的内容包括( )。",
    "options": [
      "支取业务办理方式",
      "授权支取累计限额",
      "联名账户打印卡",
      "联名账户所有人"
    ],
    "answer": [
      0,
      1,
      2
    ],
    "type": "multi",
    "note": ""
  },
  {
    "id": 77,
    "chapter": "其他",
    "text": "借款人办理个人质押贷款，全线上办理方式的，消费用途单户最高位( )万，经营用途单户最高为( )万。线上线下结合办理按用途限定最高额度，其中:消费用途单户最高( )万，经营用途单户最高( )万。单户共计可申请1280万。",
    "options": [
      "30",
      "1000",
      "50",
      "200"
    ],
    "answer": [
      0,
      1,
      2,
      3
    ],
    "type": "multi",
    "note": ""
  },
  {
    "id": 78,
    "chapter": "存款与储蓄业务",
    "text": "客户20万元的定期存款到期后，按照客户要求不直接提取或者划转，将( )续存入在同一金融机构开立的同一名下的另一账户，在业务办理过程中，客服经理如未发现交易或行为可疑的，可以不报告。",
    "options": [
      "本金",
      "本金加全部利息",
      "本金加部分利息",
      "利息"
    ],
    "answer": [
      0,
      1,
      2
    ],
    "type": "multi",
    "note": ""
  },
  {
    "id": 79,
    "chapter": "电子银行业务",
    "text": "个人贷记卡在网上银行不能进行下面哪些调额操作( )",
    "options": [
      "信用卡总额度内的账户额度调整",
      "超过信用卡总额度的账户额度调整",
      "人民币账户与外币账户间的额度调剂",
      "预审批额度内的总额度调整"
    ],
    "answer": [
      1,
      2,
      3
    ],
    "type": "multi",
    "note": ""
  },
  {
    "id": 80,
    "chapter": "贵金属业务",
    "text": "以下哪些是品牌贵金属产品的销售渠道( )。",
    "options": [
      "柜面渠道",
      "自助渠道",
      "融E购工银金行家旗舰店",
      "工银E定制微信小程序",
      "获授权的第三方渠道"
    ],
    "answer": [
      0,
      1,
      2,
      3,
      4
    ],
    "type": "multi",
    "note": ""
  },
  {
    "id": 81,
    "chapter": "账户管理",
    "text": "下列账户应用号正确的是( )。",
    "options": [
      "01活期",
      "02定期存单",
      "11内部户",
      "35法人本外币理财"
    ],
    "answer": [
      0,
      1,
      2
    ],
    "type": "multi",
    "note": ""
  },
  {
    "id": 82,
    "chapter": "基金业务",
    "text": "投资者所持有的基金在出现以下( ) 情况时，投资者就需要重新审视现有的基金组合，适当地采取调整措施。",
    "options": [
      "基金策略和风格转变",
      "基金投资表现持续落后",
      "基金规模变得过大",
      "基金经理变更"
    ],
    "answer": [
      0,
      1,
      2,
      3
    ],
    "type": "multi",
    "note": ""
  },
  {
    "id": 83,
    "chapter": "其他",
    "text": "内部户是指用于核算内部资金往来的帐户，包括( )和损益类帐户。",
    "options": [
      "内部资产类帐户",
      "内部负债类帐户",
      "所有者权益类帐户",
      "资产负债共同类帐户"
    ],
    "answer": [
      0,
      1,
      2,
      3
    ],
    "type": "multi",
    "note": ""
  },
  {
    "id": 84,
    "chapter": "账户管理",
    "text": "对于单位账户出现下列异常情形之一的，应执行只收不付控制措施( )",
    "options": [
      "被撤并、解散、宣告破产或关闭以及注销、被吊销营业执照或国家市场监督管理部门不再为其换发已到期营业执照，且超过5个工作日未向开户行提交撤销单位账户申请",
      "单位名称、法定代表人或单位负责人发生变更，客户经理等管户人员通知客户之日起满30日后，单位客户未办理变更手续，且未提出合理理由",
      "被全国企业信用信息公示系统列入“严重违法失信企业名单”",
      "应配合我行参加账户年检，但拒不配合，且未提出合理理由"
    ],
    "answer": [
      0,
      1,
      2,
      3
    ],
    "type": "multi",
    "note": ""
  },
  {
    "id": 85,
    "chapter": "电子银行业务",
    "text": "个人网上银行的第三方存管功能功能包括:( )。",
    "options": [
      "相关查询交易",
      "银行转证券公司",
      "证券公司转银行",
      "银行转期货公司"
    ],
    "answer": [
      0,
      1,
      2
    ],
    "type": "multi",
    "note": ""
  },
  {
    "id": 86,
    "chapter": "票据结算",
    "text": "在( )情况下，银行汇票不得背书转让。",
    "options": [
      "未填明实际结算金额",
      "多余金额超过出票金额",
      "实际结算金额超过出票金额",
      "实际结算金额小于出票金额",
      "实际结算金额等于出票金额"
    ],
    "answer": [
      0,
      1,
      2
    ],
    "type": "multi",
    "note": ""
  },
  {
    "id": 87,
    "chapter": "现金业务与自助机具",
    "text": "办理现金业务必须坚持“日清日结”，做到( )相符。",
    "options": [
      "账款",
      "账实",
      "账账",
      "账册"
    ],
    "answer": [
      0,
      1,
      2
    ],
    "type": "multi",
    "note": ""
  },
  {
    "id": 88,
    "chapter": "其他",
    "text": "客服经理电话营销沟通技巧主要包括",
    "options": [
      "把握时机",
      "通话语言条理清晰",
      "适可而止",
      "创造需求"
    ],
    "answer": [
      0,
      1,
      2,
      3
    ],
    "type": "multi",
    "note": ""
  },
  {
    "id": 89,
    "chapter": "其他",
    "text": "受理单位客户信息变更业务，客服经理应对( )进行审查。",
    "options": [
      "变更事项是否属实",
      "证明文件是否符合规定",
      "属于授权办理的，授权书是否由法定代表人或单位负责人签章，授权事项是否明确且与所办业务一致"
    ],
    "answer": [
      0,
      1,
      2,
      3
    ],
    "type": "multi",
    "note": ""
  },
  {
    "id": 90,
    "chapter": "其他",
    "text": "营业中，客服经理实施柜台内外灵活补位时，要按规定做好( )等的保管和交接，并签退相关系统，确保安全运营。",
    "options": [
      "现金",
      "空白重要凭证",
      "移动助手",
      "重要物品"
    ],
    "answer": [
      0,
      1,
      2,
      3
    ],
    "type": "multi",
    "note": ""
  },
  {
    "id": 91,
    "chapter": "信用卡业务",
    "text": "客户使用预留的( )号码可以通过电话银行人工服务办理信用卡卡片启用。",
    "options": [
      "家庭电话",
      "手机号码",
      "单位电话",
      "联系人电话"
    ],
    "answer": [
      0,
      1
    ],
    "type": "multi",
    "note": ""
  },
  {
    "id": 92,
    "chapter": "厅堂与客户服务",
    "text": "融E联可以提供以下( )服务。",
    "options": [
      "联系客户经理",
      "开立二类账户",
      "定制工银信使",
      "在部分地区查询社保信息"
    ],
    "answer": [
      0,
      2,
      3
    ],
    "type": "multi",
    "note": ""
  },
  {
    "id": 93,
    "chapter": "其他",
    "text": "远程授权相关岗位包括( )。",
    "options": [
      "业务经办",
      "业务主办",
      "远程授权岗",
      "现场管理人员"
    ],
    "answer": [
      0,
      2,
      3
    ],
    "type": "multi",
    "note": ""
  },
  {
    "id": 94,
    "chapter": "厅堂与客户服务",
    "text": "网点智能服务模式的目标是( )。",
    "options": [
      "交易处理离柜化",
      "业务流程精简化",
      "产品营销协同化",
      "客户体验人性化"
    ],
    "answer": [
      0,
      1,
      2,
      3
    ],
    "type": "multi",
    "note": ""
  },
  {
    "id": 95,
    "chapter": "其他",
    "text": "手工挂账业务应提交《手工挂账业务申请表》，并遵循以下级次进行审批，严禁越级、超范围审批和授权。以下说法正确的是( )",
    "options": [
      "金额1万元(含)以下的，由一级支行审批",
      "金额1万元(不含)以下的，由-级支行审批",
      "金额1万元(含)以上50万元(不含)以下的，由二级分行业务管理部门申请、资产负债部门和财务会计部门审批，运行管理部门组织实施",
      "金额1万元(不含)以上50万元(不含)以下的，由二级分行业务管理部门申请、资产负债部门和财务会计部门审批，运行管理部门组织实施"
    ],
    "answer": [
      1,
      2
    ],
    "type": "multi",
    "note": ""
  },
  {
    "id": 96,
    "chapter": "存款与储蓄业务",
    "text": "投资类存款是指存款人以获得利息为目的存入银行，不具备支付结算功能的存款，包括( )。A.外币存款",
    "options": [
      "人民币的单位定期存款",
      "个人活期储蓄存款",
      "个人定期储蓄存款"
    ],
    "answer": [
      0,
      1,
      2,
      3
    ],
    "type": "multi",
    "note": ""
  },
  {
    "id": 97,
    "chapter": "其他",
    "text": "对于网点的以下哪些行为我们应严格禁止( ) L44",
    "options": [
      "擅自停止营业，或不按照网点公示的开、关门时间营业，无故缩短营业时间",
      "使用服务忌语、态度冷漠粗暴、无正当理由拒办业务、顶撞客户、与客户争吵或发生肢体冲突等C.在营业场所内吸烟、喝酒、吃零食、把玩私人物品、把玩手机、娱乐、擅离岗位、串岗、打瞌睡等失范行为",
      "不尊重客户对业务办理渠道和方式的自主选择，强制分流客户"
    ],
    "answer": [
      0,
      1,
      2,
      3
    ],
    "type": "multi",
    "note": ""
  },
  {
    "id": 98,
    "chapter": "其他",
    "text": "境内各支行及营业网点负责主要履行的职责包括:",
    "options": [
      "做好客户准入环节的身份信息资料采集、核实、登记和保存等工作，确保客户身份信息完整、真实、有效",
      "做好业务存续期内的客户信息维护、以及持续识别、重新识别相关尽职调查工作(资金交易分析除外)",
      "做好客户身份资料的完整传送和档案管理",
      "落实上级行客户身份识别工作部署，配合当地监管及上级行客户身份识别检查，及时整改检查发现问题"
    ],
    "answer": [
      0,
      1,
      2,
      3
    ],
    "type": "multi",
    "note": ""
  },
  {
    "id": 99,
    "chapter": "票据结算",
    "text": "票据法所称票据权利，是指持票人向票据债务人请求支付票据金额的权利，包括( )。A.知情权",
    "options": [
      "付款请求权",
      "优先权",
      "追索权",
      "使用权"
    ],
    "answer": [
      1,
      3
    ],
    "type": "multi",
    "note": ""
  },
  {
    "id": 100,
    "chapter": "反洗钱与大额交易",
    "text": "对于销户时账户转出金额对达到或超过( )客服经理必须按照反洗钱操作规定进行审核。A.人民币5千元",
    "options": [
      "人民币5万元",
      "外币等值5千美元",
      "外币等值1万美元"
    ],
    "answer": [
      1,
      3
    ],
    "type": "multi",
    "note": ""
  },
  {
    "id": 101,
    "chapter": "其他",
    "text": "目前，客户可以通过( )渠道对订单进行支付。",
    "options": [
      "电话银行",
      "柜面",
      "网上银行",
      "手机银行"
    ],
    "answer": [
      1,
      2,
      3
    ],
    "type": "multi",
    "note": ""
  },
  {
    "id": 102,
    "chapter": "个人外汇业务",
    "text": "“外汇金融”服务方案的目标客户主要是具有一定经济基础、收入较高的中高端客户，对本外币金融资产配置有较大的兴趣和需求。服务内容包括外汇资产管理、外汇投资交易和其他外汇服务，具体产品包括( )",
    "options": [
      "个人出境保证金",
      "个人外汇储蓄存款",
      "个人外汇理财",
      "账户能源及账户贵金属"
    ],
    "answer": [
      1,
      2,
      3
    ],
    "type": "multi",
    "note": ""
  },
  {
    "id": 103,
    "chapter": "其他",
    "text": "下列哪些业务需要对客户进行身份联网核查( )。",
    "options": [
      "汇款人以现金方式申请办理个人汇款或以转账方式申请办理大额个人汇款(金额在5万元以上)B.客户办理异地存取款时，金额超过5万元(不含5万元)或银行卡磁性受损",
      "账户开立",
      "储蓄账户密码重置"
    ],
    "answer": [
      0,
      1,
      2,
      3
    ],
    "type": "multi",
    "note": ""
  },
  {
    "id": 104,
    "chapter": "其他",
    "text": "全行实施网点新岗位体系建设后，营业网点统一设置( )等岗位。",
    "options": [
      "网点负责人",
      "运营主管",
      "客服经理",
      "柜员",
      "客户经理"
    ],
    "answer": [
      0,
      1,
      2,
      4
    ],
    "type": "multi",
    "note": ""
  },
  {
    "id": 105,
    "chapter": "贵金属业务",
    "text": "贵金属实物产品应按照( ) 分箱(柜)管理，不得混放",
    "options": [
      "权属",
      "种类",
      "规格"
    ],
    "answer": [
      0,
      1,
      2
    ],
    "type": "multi",
    "note": ""
  },
  {
    "id": 106,
    "chapter": "存款与储蓄业务",
    "text": "个人通知存款应约定提前通知取款时间，不约定存期，支取前需按约定将取款时间提前通知银行，按约定日期支取存款，分为( )两个品种。",
    "options": [
      "-天个人通知存款",
      "七天个人通知存款",
      "双周个人通知存款",
      "月度个人通知存款"
    ],
    "answer": [
      0,
      1
    ],
    "type": "multi",
    "note": ""
  },
  {
    "id": 107,
    "chapter": "其他",
    "text": "业务集中应急处理包括( )、",
    "options": [
      "备份中心应急处理",
      "业务处理中心处理",
      "分散网点联机处理",
      "灾备系统处理"
    ],
    "answer": [
      0,
      2
    ],
    "type": "multi",
    "note": ""
  },
  {
    "id": 108,
    "chapter": "电子银行业务",
    "text": "我行电子银行服务四大渠道包括( )。",
    "options": [
      "网.上银行",
      "电话银行",
      "手机银行",
      "自助银行"
    ],
    "answer": [
      0,
      1,
      2,
      3
    ],
    "type": "multi",
    "note": ""
  },
  {
    "id": 109,
    "chapter": "其他",
    "text": "变造的货币是指在真币的基础上，利用( )重印等多种方法制作，改变真币原形态的假币。A.挖补",
    "options": [
      "揭层",
      "涂改",
      "拼凑",
      "移位"
    ],
    "answer": [
      0,
      1,
      2,
      3,
      4
    ],
    "type": "multi",
    "note": ""
  },
  {
    "id": 110,
    "chapter": "厅堂与客户服务",
    "text": "客服经理依托PBMS系统开展目标客户关系维护，可以通过如下( )等方式开展信息提醒、业务介绍、产品推荐、服务邀约、情感维护等日常关系维护工作。",
    "options": [
      "微信",
      "批量短信",
      "融E联",
      "支付宝"
    ],
    "answer": [
      1,
      2
    ],
    "type": "multi",
    "note": ""
  },
  {
    "id": 111,
    "chapter": "其他",
    "text": "远程授权相关岗位包括( )。",
    "options": [
      "业务经办人员",
      "现场管理人员",
      "远程授权岗",
      "远程监督岗"
    ],
    "answer": [
      0,
      1,
      2
    ],
    "type": "multi",
    "note": ""
  },
  {
    "id": 112,
    "chapter": "厅堂与客户服务",
    "text": "网点智能服务的业务处理方式主要包括( )。",
    "options": [
      "“自助”",
      "“自助+人脸识别”",
      "“自助+单人核验”",
      "“自助+人脸识别+人工核验”",
      "“自助+双人核验”"
    ],
    "answer": [
      0,
      1,
      2,
      3,
      4
    ],
    "type": "multi",
    "note": ""
  },
  {
    "id": 113,
    "chapter": "其他",
    "text": "汇率又称( )，简称( )，是指一国货币兑换成另一国货币的比率;也可以说，是以本国货币表示的外国货币的“价格”。",
    "options": [
      "外汇汇价",
      "外汇牌价",
      "外汇行市",
      "牌价"
    ],
    "answer": [
      0,
      1,
      2,
      3
    ],
    "type": "multi",
    "note": ""
  },
  {
    "id": 114,
    "chapter": "现金业务与自助机具",
    "text": "柜面处理现金业务尤其是大额现金业务时应做到( )",
    "options": [
      "主动提示客户注意介质安全及密码安全",
      "严格执行唱收唱付，声音洪亮地告诉客户金额",
      "当客户显现被诈骗的苗头时，主动提醒诈骗风险，劝阻客户停止办理业务，防止资金受损D.注意语言私密性，防止泄露客户敏感信息"
    ],
    "answer": [
      0,
      2,
      3
    ],
    "type": "multi",
    "note": ""
  },
  {
    "id": 115,
    "chapter": "存款与储蓄业务",
    "text": "若联网核查无法确认身份证真实有效，或客户提供的身份证件为非居民身份证，在满足客户提供本人( )等相关辅助资料证明客户为存款人本人，并能提供个人存款凭证，账户余额在人民币1000元(含)以下，且客户同意销户等条件的基础上，可实时为客户办理密码重置，并按照个人存款凭证销户有关规定为客户办理销户手续。",
    "options": [
      "户口簿",
      "驾驶执照",
      "护照",
      "社保卡"
    ],
    "answer": [
      0,
      1,
      2,
      3
    ],
    "type": "multi",
    "note": ""
  },
  {
    "id": 116,
    "chapter": "其他",
    "text": "关于飞单私售的问责，管理人员要按照“一案双查、双线追究”原则严肃追究责任，以下哪几种行为要坚决给予免职、撤职或解除劳动合同处分处罚( )。",
    "options": [
      "授意员工违规",
      "指使员工违规",
      "包庇员工违规",
      "纵容员工违规"
    ],
    "answer": [
      0,
      1,
      2,
      3
    ],
    "type": "multi",
    "note": ""
  },
  {
    "id": 117,
    "chapter": "其他",
    "text": "客户可通过( )渠道购买我行销售的法人理财产品。",
    "options": [
      "柜面渠道",
      "企业网上银行",
      "企业手机银行",
      "智能终端"
    ],
    "answer": [
      0,
      1,
      2
    ],
    "type": "multi",
    "note": ""
  },
  {
    "id": 118,
    "chapter": "运营风险与内控",
    "text": "会计凭证以客服经理为单位，按事中已扫描凭证和事后待扫描凭证分别摆放。事后待扫描的会计凭证应按( )分别整理，可使用复写板等进行分隔。",
    "options": [
      "轧账单",
      "有流水号凭证",
      "报表"
    ],
    "answer": [
      0,
      1,
      2
    ],
    "type": "multi",
    "note": ""
  },
  {
    "id": 119,
    "chapter": "其他",
    "text": "影响汇率的因素包括:",
    "options": [
      "政治因素",
      "宏观经济",
      "通货膨胀",
      "市场因素"
    ],
    "answer": [
      0,
      1,
      2,
      3
    ],
    "type": "multi",
    "note": ""
  },
  {
    "id": 120,
    "chapter": "其他",
    "text": "网点可发起的消息类型分为( )。",
    "options": [
      "重要消息",
      "普通消息",
      "广播消息",
      "优先级调整消息"
    ],
    "answer": [
      0,
      1,
      3
    ],
    "type": "multi",
    "note": ""
  },
  {
    "id": 121,
    "chapter": "账户管理",
    "text": "同业账户按账户开立方向分为( )和( )两类。",
    "options": [
      "同业存放账户",
      "结算性同业账户",
      "投融资性同业账户",
      "存放同业账户"
    ],
    "answer": [
      1,
      2
    ],
    "type": "multi",
    "note": ""
  },
  {
    "id": 122,
    "chapter": "运营风险与内控",
    "text": "产品领取机内核算要素的( )应在监控下完成。",
    "options": [
      "加装",
      "清点",
      "上缴"
    ],
    "answer": [
      0,
      1,
      2
    ],
    "type": "multi",
    "note": ""
  },
  {
    "id": 123,
    "chapter": "其他",
    "text": "根据我行客户身份识别的要求，在对客户进行初次识别时，应采取的措施包括:",
    "options": [
      "基础材料采集",
      "基础信息登记",
      "基础信息核验",
      "基础材料留存"
    ],
    "answer": [
      0,
      1,
      2,
      3
    ],
    "type": "multi",
    "note": ""
  },
  {
    "id": 124,
    "chapter": "信用卡业务",
    "text": "牡丹信用卡分期付款的消费起点是( ) 元。",
    "options": [
      "人民币600",
      "港币800",
      "美元100",
      "人民币100"
    ],
    "answer": [
      2,
      3
    ],
    "type": "multi",
    "note": ""
  },
  {
    "id": 125,
    "chapter": "其他",
    "text": "根据管理信息部《关于印发个人客户信息统计制度的通知》(工银办发[2010]888 号)规定，个人客户金融资产统计范围包括( )。",
    "options": [
      "储蓄存款",
      "理财产品",
      "基金",
      "保险"
    ],
    "answer": [
      0,
      1,
      2,
      3
    ],
    "type": "multi",
    "note": ""
  },
  {
    "id": 126,
    "chapter": "其他",
    "text": "融E行目前已推出了哪些个性化版本( )",
    "options": [
      "美好家园版",
      "幸福生活版",
      "校园版",
      "私人银行版"
    ],
    "answer": [
      0,
      1,
      2,
      3
    ],
    "type": "multi",
    "note": ""
  },
  {
    "id": 127,
    "chapter": "账户管理",
    "text": "下列哪些属于财智账户卡的安全控制手段?",
    "options": [
      "卡密码",
      "支付密码器动态密码",
      "支付权限控制",
      "渠道额度控制"
    ],
    "answer": [
      0,
      1,
      2,
      3
    ],
    "type": "multi",
    "note": ""
  },
  {
    "id": 128,
    "chapter": "其他",
    "text": "以下关于网点员工关怀的描述正确的是( )",
    "options": [
      "网点室内冬季温度不得低于18摄氏度，夏季温度维持在26摄氏度左右",
      "网点应注意对经常无理恶意投诉，或借投诉之名行索要不正当利益之实的客户的对待处理，抵制不合理诉求，保护好涉事员工",
      "在客户投诉处理过程中，既不得推诿扯皮，也不得一味委屈求全，有原则、有尊严地做好客户服务工作",
      "网点应通过加装新风系统或设置通风口、增配空气净化器等方式，以保持空气流通"
    ],
    "answer": [
      0,
      1,
      2,
      3
    ],
    "type": "multi",
    "note": ""
  },
  {
    "id": 129,
    "chapter": "其他",
    "text": "客服经理为客户发送短信的方式包括( )",
    "options": [
      "标准模板",
      "固定模板",
      "套用模板",
      "手工编辑"
    ],
    "answer": [
      1,
      2,
      3
    ],
    "type": "multi",
    "note": ""
  },
  {
    "id": 130,
    "chapter": "其他",
    "text": "录入军人证件号码时，( )。",
    "options": [
      "证件号码不超过18个字符(9 个汉字)的，按照证件号码完整输入，不必录入空格",
      "证件号码超过18个字符(9个汉字)的，将“第”、“号”两字同时忽略不填，",
      "如果仍然超过18个字符(9 个汉字)，则从数字左侧依次往左删除文字，直至长度小于等于18个字符(9个汉字)",
      "证件号码超过18个字符(9个汉字)的，自左向右录入。"
    ],
    "answer": [
      0,
      1,
      2
    ],
    "type": "multi",
    "note": ""
  },
  {
    "id": 131,
    "chapter": "账户管理",
    "text": "满足( )等条件，办理个人小额账户挂失与密码重置业务有关流程简化为“可实时为客户办理挂失销户”。",
    "options": [
      "联网核查确认身份证真实有效",
      "账户余额在人民币300元(含)以下",
      "账户余额在人民币1000元(含)以下",
      "客户同意挂失销户等条件",
      "客户同意挂失换卡(折)"
    ],
    "answer": [
      0,
      2,
      3
    ],
    "type": "multi",
    "note": ""
  },
  {
    "id": 132,
    "chapter": "其他",
    "text": "如确认或有合理理由怀疑客户列入联合国制裁名单，应该怎样处理( )",
    "options": [
      "立即采取相应的交易限制措施",
      "将情况立即逐级上报总行，确保总行能够当日向人民银行总行报告或申请核实确认",
      "在符合监管部门、司法机关及我行保密要求的前提下，及时向客户进行解释说明，递交适用于受联合国制裁情况的《客户告知书》",
      "对经人民银行核实客户不属制裁名单，或客户被解除制裁的情况，应根据总行通知立即终止所采取措施"
    ],
    "answer": [
      0,
      1,
      2,
      3
    ],
    "type": "multi",
    "note": ""
  },
  {
    "id": 133,
    "chapter": "其他",
    "text": "网点日间特殊处理包括( )等。",
    "options": [
      "退回业务处理",
      "业务撤销",
      "业务查询",
      "消息处理"
    ],
    "answer": [
      0,
      1,
      2,
      3
    ],
    "type": "multi",
    "note": ""
  },
  {
    "id": 134,
    "chapter": "其他",
    "text": "无固定期限超短期理财产品的交易方式包括",
    "options": [
      "柜面主动申赎",
      "网银主动申赎",
      "协议自动申赎",
      "智能终端主动申赎"
    ],
    "answer": [
      0,
      1,
      2
    ],
    "type": "multi",
    "note": ""
  },
  {
    "id": 135,
    "chapter": "信用卡业务",
    "text": "目前，客户填写申请表申请办理我行信用卡时可同时定制的个性化服务包括但不限于( )。A.自动还款业务",
    "options": [
      "余额变动提醒",
      "EmAil账单服务",
      "实时购汇业务"
    ],
    "answer": [
      0,
      1,
      2
    ],
    "type": "multi",
    "note": ""
  },
  {
    "id": 136,
    "chapter": "厅堂与客户服务",
    "text": "智能服务模式有助于( )。",
    "options": [
      "我行网点渠道转型",
      "人员结构优化",
      "服务质量提高",
      "经营效能提升"
    ],
    "answer": [
      0,
      1,
      2,
      3
    ],
    "type": "multi",
    "note": ""
  },
  {
    "id": 137,
    "chapter": "账户管理",
    "text": "同业账户按用途分为( )和( )两类",
    "options": [
      "同业存放账户",
      "结算性同业账户",
      "投融资性同业账户",
      "存放同业账户"
    ],
    "answer": [
      1,
      2
    ],
    "type": "multi",
    "note": ""
  },
  {
    "id": 138,
    "chapter": "厅堂与客户服务",
    "text": "网点电话服务应做到( )",
    "options": [
      "对外电话信息准确",
      "电话接听及时，回答准确",
      "切实落实客户预约需求，避免误导客户",
      "营业网点应在醒目位置公布本网点与上级行服务咨询投诉电话及统-的客户投诉渠道"
    ],
    "answer": [
      0,
      1,
      2,
      3
    ],
    "type": "multi",
    "note": ""
  },
  {
    "id": 139,
    "chapter": "其他",
    "text": "下列关于资本项目业务登记编号说法正确的是",
    "options": [
      "资本项目业务编号，由资本项目信息系统生成",
      "资本项目业务编号前两位为业务类型标识",
      "资本项目业务编号第3至8位为外汇局代码",
      "资本项目业务编号第9至16位为8位年月日"
    ],
    "answer": [
      0,
      1,
      2,
      3
    ],
    "type": "multi",
    "note": ""
  },
  {
    "id": 140,
    "chapter": "电子银行业务",
    "text": "信用卡客户可以在哪些渠道注销个人网上银行( )",
    "options": [
      "登陆个人网银",
      "自助存款机",
      "电话银行",
      "营业网点"
    ],
    "answer": [
      0,
      3
    ],
    "type": "multi",
    "note": ""
  },
  {
    "id": 141,
    "chapter": "运营风险与内控",
    "text": "影像校验是对系统未能自动勾对的凭证影像和日志进行人工处理，以及对已建立精确索引的凭证影像进行追加、替换等操作，主要包括日结校验和( )三个部分。",
    "options": [
      "影像应用",
      "特殊操作",
      "影像质检",
      "事中影像追加"
    ],
    "answer": [
      1,
      3
    ],
    "type": "multi",
    "note": ""
  },
  {
    "id": 142,
    "chapter": "其他",
    "text": "遇到系统中已建立的个人客户身份证号码与申请开户的客户重号，联网核查已有的证件信息，提示“身份证号码存在，但与姓名不匹配”，且联网核查申请开户的客户证件信息无误时，客服经理需分别打印核查结果，并( )",
    "options": [
      "删除系统中已有的客户信息，删除成功后可为申请开户的客户办理业务;",
      "无法删除已有的客户信息时，查询该信息的相关要素，填写《居民身份证重号处理表》;C.客服经理将已有客户信息的证件类型修改为“其他”，将客户信息设置“待核实”标志;D.完成上述处理后，为开户客户正常办理业务。"
    ],
    "answer": [
      0,
      1,
      2,
      3
    ],
    "type": "multi",
    "note": ""
  },
  {
    "id": 143,
    "chapter": "其他",
    "text": "为客户办理理财业务时，应提醒客户认真阅读产品说明书及销售文本，并向客户充分揭示)",
    "options": [
      "风险等级",
      "承诺收益",
      "投资方向",
      "产品期限"
    ],
    "answer": [
      0,
      2,
      3
    ],
    "type": "multi",
    "note": ""
  },
  {
    "id": 144,
    "chapter": "其他",
    "text": "远程授权的管理原则为( )。",
    "options": [
      "逐级审批原则",
      "风险导向原则",
      "提高效率原则",
      "改进服务原则"
    ],
    "answer": [
      1,
      2,
      3
    ],
    "type": "multi",
    "note": ""
  },
  {
    "id": 145,
    "chapter": "其他",
    "text": "特殊残缺、污损人民币是指票面因( ) 等特殊原因，造成外观、质地、防伪特征受损，纸张碳化、变形，图案不清晰，不宜再继续流通使用的人民币。",
    "options": [
      "火灾",
      "虫蛀",
      "鼠咬",
      "霉烂"
    ],
    "answer": [
      0,
      1,
      2,
      3
    ],
    "type": "multi",
    "note": ""
  },
  {
    "id": 146,
    "chapter": "账户管理",
    "text": "如客户申请变更核准类结算账户的( )，还应及时将《变更申请书》、开户许可证及相关证明文件报送人民银行当地分支行，人民银行核准后方可办理变更手续。",
    "options": [
      "账户名称",
      "法定代表人或单位负责人",
      "单位地址",
      "其他开户资料"
    ],
    "answer": [
      0,
      1,
      2,
      3
    ],
    "type": "multi",
    "note": ""
  },
  {
    "id": 147,
    "chapter": "现金业务与自助机具",
    "text": "联名卡支取业务办理方式指联名账户所有人办理联名账户支取业务(含现金支取和转账支取)时的处理方式，分为( )。",
    "options": [
      "联名办理",
      "共同办理",
      "合同办理",
      "授权办理"
    ],
    "answer": [
      1,
      3
    ],
    "type": "multi",
    "note": ""
  },
  {
    "id": 148,
    "chapter": "电子银行业务",
    "text": "下列功能中，属于企业网上银行贵宾室业务功能的有:( )。",
    "options": [
      "综合收付款",
      "预约服务",
      "自动收款",
      "企业财务室"
    ],
    "answer": [
      1,
      2,
      3
    ],
    "type": "multi",
    "note": ""
  },
  {
    "id": 149,
    "chapter": "个人外汇业务",
    "text": "开户行为境内机构、驻华使领馆、国际组织驻华机构开立外汇账户时须审核以下材料( ):A.境内机构外汇账户开立申请书",
    "options": [
      "外汇局数字外管平台查询打印客户主体档案信息结果，与开户资料一并留存;",
      "法定代表人或单位负责人有效身份证件以及营业执照或其他设立证明文件",
      "外汇，局或开户行要求提供的相关协议及其他资料"
    ],
    "answer": [
      0,
      1,
      2,
      3
    ],
    "type": "multi",
    "note": ""
  },
  {
    "id": 150,
    "chapter": "信用卡业务",
    "text": "以下哪些不是我行信用卡分期付款的期数( )",
    "options": [
      "24期",
      "18期",
      "10期",
      "8期"
    ],
    "answer": [
      2,
      3
    ],
    "type": "multi",
    "note": ""
  },
  {
    "id": 151,
    "chapter": "其他",
    "text": "我行面向合格投资者代理推广证券公司发行的集合资产管理计划的业务描述正确的是( )A.可以公开营销宣传",
    "options": [
      "严禁向投资人承诺本金不受损失或承诺最低收益",
      "面向具有一定投资经验，具备一定风险识别和风险承担能力的合格投资者",
      "面向所有投资者"
    ],
    "answer": [
      1
    ],
    "type": "multi",
    "note": ""
  },
  {
    "id": 152,
    "chapter": "其他",
    "text": "下列关于个人客户信息调整的相关规定，说法正确的有( )",
    "options": [
      "客户需持符合实名制要求的本人有效身份证件办理客户信息的变更业务。该业务不得代办",
      "客服经理审核客户本人身份证件真实有效后方可办理。当客户证件为居民身份证时，使用“公民身份信息查询”交易核实客户身份证信息的真实性和有效性",
      "客户主动申请变更身份信息时( 包括客户信息中的户名、证件号码、证件类型)，只需要提供本人",
      "客户信息系统的调整必须经有权人授权处理"
    ],
    "answer": [
      0,
      1,
      3
    ],
    "type": "multi",
    "note": ""
  },
  {
    "id": 153,
    "chapter": "存款与储蓄业务",
    "text": "个人存款异地托收种类包括( )。",
    "options": [
      "本外币活期、定期(含定期存单和定期一本通)定活两便",
      "零存整取",
      "存本取息储蓄存单(折)到期或未到期存款的全额",
      "大额可转让定期存单"
    ],
    "answer": [
      0,
      1,
      2
    ],
    "type": "multi",
    "note": ""
  },
  {
    "id": 154,
    "chapter": "其他",
    "text": "下列关于个人客户信息的基本规定说法错误的是( )。",
    "options": [
      "可以将客户信息内容随意提供给其他单位或个人",
      "任何人不得利用客户信息谋取私利",
      "客服经理在为客户办理证件类型、号码、户名变更或内部查询时，无须核验客户有效身份证件真实有效",
      "客户信息的调整由客服经理人前台操作即可完成，不需经有权人员审核授权。"
    ],
    "answer": [
      0,
      2,
      3
    ],
    "type": "multi",
    "note": ""
  },
  {
    "id": 155,
    "chapter": "账户管理",
    "text": "II类、I账户的开户渠道包括( )",
    "options": [
      "银行柜面",
      "网银、手机银行",
      "智能柜员机",
      "远程视频柜员机"
    ],
    "answer": [
      0,
      1,
      2,
      3
    ],
    "type": "multi",
    "note": ""
  },
  {
    "id": 156,
    "chapter": "个人外汇业务",
    "text": "个人外汇账户按交易主体类别和交易性质进行管理。按交易性质分为经常项目和资本项目，经常项目账户包括( )",
    "options": [
      "个人外汇储蓄账户",
      "个人外汇结算账户",
      "投资并购专用账户",
      "外国投资者投资专用账户"
    ],
    "answer": [
      0,
      1
    ],
    "type": "multi",
    "note": ""
  },
  {
    "id": 157,
    "chapter": "运营风险与内控",
    "text": "客户通过线下渠道预约申请凭证出售时，应向网点提交( )等。",
    "options": [
      "经办人员名章",
      "身份证件",
      "财智账户卡",
      "单位预留印鉴"
    ],
    "answer": [
      1,
      2
    ],
    "type": "multi",
    "note": ""
  },
  {
    "id": 158,
    "chapter": "运营风险与内控",
    "text": "远程业务中在不影响要素完整性与清晰性的前提下，可将相关资料合屏传输。凡凭证中填有客户身份信息的一面应与( )合屏传输，另一面则与( )合屏传输。",
    "options": [
      "身份证正面",
      "身份证反面",
      "身份证原件",
      "身份证复印件"
    ],
    "answer": [
      0,
      1
    ],
    "type": "multi",
    "note": ""
  },
  {
    "id": 159,
    "chapter": "信用卡业务",
    "text": "信用卡持卡人可通过( )渠道进行取款",
    "options": [
      "网上银行",
      "ATM",
      "本行网点柜面",
      "他行网点柜面"
    ],
    "answer": [
      1,
      2
    ],
    "type": "multi",
    "note": ""
  },
  {
    "id": 160,
    "chapter": "厅堂与客户服务",
    "text": "客户维护任务中的产品到期承接支持查看客户多久到期明细( )",
    "options": [
      "当日",
      "明日",
      "7天",
      "14天",
      "21天"
    ],
    "answer": [
      0,
      1,
      2,
      3,
      4
    ],
    "type": "multi",
    "note": ""
  },
  {
    "id": 161,
    "chapter": "其他",
    "text": "以下说法正确的是( ).",
    "options": [
      "客户与我行约定使用支付密码的，应要求客户自约定之日起，在支付凭证上签署有效的支付密码，并加盖预留银行签章，银行凭以审核支付。",
      "支付密码错误的，视同签章与预留不符处理。",
      "未加盖预留银行签章的，不得受理。",
      "支付密码经办柜员不得保管或出售与其操作的支付密码构成支付要件的空白重要凭证。"
    ],
    "answer": [
      0,
      1,
      2,
      3
    ],
    "type": "multi",
    "note": ""
  },
  {
    "id": 162,
    "chapter": "信用卡业务",
    "text": "持卡人可以通过哪几种渠道查询牡丹个人信用卡对账单( )",
    "options": [
      "网上银行",
      "电话银行",
      "网点柜面",
      "手机银行"
    ],
    "answer": [
      0,
      1,
      2,
      3
    ],
    "type": "multi",
    "note": ""
  },
  {
    "id": 163,
    "chapter": "信用卡业务",
    "text": "按照信用等级可将我行信用卡分为( )",
    "options": [
      "黑金卡",
      "金卡",
      "普通卡",
      "白金卡"
    ],
    "answer": [
      0,
      1,
      2,
      3
    ],
    "type": "multi",
    "note": ""
  },
  {
    "id": 164,
    "chapter": "现金业务与自助机具",
    "text": "营业网点钱箱管理必须严格执行现金业务操作规程，坚持( )，营业网点现场管理人员对“9999钱箱”的库存现金的真实性负有监督责任。",
    "options": [
      "“99999钱箱\"实物双人管理",
      "共同负责",
      "现金实物、钱箱查询余额、网点现金日结单核对"
    ],
    "answer": [
      0,
      1,
      2,
      3
    ],
    "type": "multi",
    "note": ""
  },
  {
    "id": 165,
    "chapter": "其他",
    "text": "事权划分遵循“( )”的原则。",
    "options": [
      "职责清晰",
      "标准统一",
      "风险可控",
      "效率优先"
    ],
    "answer": [
      0,
      1,
      2,
      3
    ],
    "type": "multi",
    "note": ""
  }
]
